timepipe/__init__.py
timepipe/event.py
timepipe-0.2.0.dist-info/LICENSE
timepipe-0.2.0.dist-info/METADATA
timepipe-0.2.0.dist-info/WHEEL
timepipe-0.2.0.dist-info/top_level.txt
timepipe-0.2.0.dist-info/RECORD
