Metadata-Version: 2.1
Name: timepipe
Version: 0.2.0
Summary: A multi-events timestamp visualizer
Home-page: https://github.com/VegaDeg/Timepipe
Author: fancy
Author-email: ruomengfan@outlook.com
Project-URL: Bug Tracker, https://github.com/VegaDeg/Timepipe
Classifier: Programming Language :: Python :: 3
Classifier: License :: OSI Approved :: MIT License
Classifier: Operating System :: OS Independent
Requires-Python: >=3.6
License-File: LICENSE
